{
  "name": "Halo",
  "category": "\ud83c\udd37 Halo",
  "info": {
    "poster": "https://image.tmdb.org/t/p/w220_and_h330_face/4UmNhZCEu8Vt3byMvNxNEPyf8EY.jpg",
    "bg": "https://image.tmdb.org/t/p/w500_and_h282_face/zW0v2YT74C6tRafzqqBkfSqLAN0.jpg",
    "plot": "Depicting an epic 26th-century conflict between humanity and an alien threat known as the Covenant, the series weaves deeply drawn personal stories with action, adventure and a richly imagined vision of the future.",
    "rating": "8.266",
    "genre": [
      "sci-fi & fantasy",
      "action & adventure"
    ],
    "cast": [
      "Pablo Schreiber",
      "Natascha McElhone",
      "Joseph Morgan",
      "Shabana Azmi",
      "Christina Bennington"
    ]
  },
  "seasons": [
    {
      "season": 1,
      "info": {
        "poster": "https://image.tmdb.org/t/p/w220_and_h330_face/6POUWaWa6BCxYlhfcKQ3woNLupv.jpg",
        "bg": "https://image.tmdb.org/t/p/w500_and_h282_face",
        "plot": "",
        "year": "2022",
        "trailer": ""
      },
      "episodes": [
        {
          "episode": 1,
          "name": "Contact",
          "info": {
            "poster": "https://image.tmdb.org/t/p/w227_and_h127_bestv2/zfBMkRvJ1M859881quboW3mnwEr.jpg",
            "plot": "In the year 2552, humans on the planet Madrigal have been fighting for independence from Earth, but a fatal encounter with the Alien Covenant complicates things. Master Chief John 117 and his super-soldier \u201cSpartans\u201d join the fight. After the battle, Master Chief heads to his home planet of Reach with a Madrigal survivor and a mysterious object he discovered on the planet. But a controversial order has John questioning his mission, and himself.",
            "director": [],
            "duration": 3540,
            "rating": "7.5",
            "backdrop": "https://image.tmdb.org/t/p/w500_and_h282_face/zfBMkRvJ1M859881quboW3mnwEr.jpg"
          },
          "video": ""
        },
        {
          "episode": 2,
          "name": "Unbound",
          "info": {
            "poster": "https://image.tmdb.org/t/p/w227_and_h127_bestv2/wsBa3hDCmUg3h7c6h27KqhbhCff.jpg",
            "plot": "John takes Kwan to an old friend and learns more about the mystery object, which the Covenant and Makee are determined to steal. With the alien threat growing, Dr. Halsey has a plan to deal with John\u2019s unpredictable behavior.",
            "director": [],
            "duration": 3240,
            "rating": "6.9",
            "backdrop": "https://image.tmdb.org/t/p/w500_and_h282_face/wsBa3hDCmUg3h7c6h27KqhbhCff.jpg"
          },
          "video": ""
        },
        {
          "episode": 3,
          "name": "Emergence",
          "info": {
            "poster": "https://image.tmdb.org/t/p/w227_and_h127_bestv2/7lVJdxrqk6AJLxZrRuCujbQKTp6.jpg",
            "plot": "John meets his new partner, and he discovers secrets inside his own memory. Kwan wants to return to Madrigal to continue her people\u2019s fight for independence, but Soren has other plans for her. Makee initiates her plan to retrieve the Madrigal object, with deadly consequences.",
            "director": [],
            "duration": 3240,
            "rating": "7.2",
            "backdrop": "https://image.tmdb.org/t/p/w500_and_h282_face/7lVJdxrqk6AJLxZrRuCujbQKTp6.jpg"
          },
          "video": ""
        },
        {
          "episode": 4,
          "name": "Homecoming",
          "info": {
            "poster": "https://image.tmdb.org/t/p/w227_and_h127_bestv2/20EcSRmvdQiJcxwXHoBzgGfHmvP.jpg",
            "plot": "Guided by his visions, John takes Halsey and Cortana back to where it all began, looking for answers from his past. With Soren along for protection, Kwan goes in search of an army. Meanwhile John\u2019s behavior inspires another Spartan to begin a journey of self-discovery. And Miranda discovers a possible link between the artifact and something much larger.",
            "director": [],
            "duration": 3300,
            "rating": "6.8",
            "backdrop": "https://image.tmdb.org/t/p/w500_and_h282_face/20EcSRmvdQiJcxwXHoBzgGfHmvP.jpg"
          },
          "video": ""
        },
        {
          "episode": 5,
          "name": "Reckoning",
          "info": {
            "poster": "https://image.tmdb.org/t/p/w227_and_h127_bestv2/eAPqbbHFZBrsTcZhxnoWChq2nX4.jpg",
            "plot": "On the run and out of options, Kwan and Soren have a difference of opinion. With the possibility of finding the mysterious Halo on everyone\u2019s minds, John makes a horrible discovery. And the war rears its ugly head.",
            "director": [],
            "duration": 2400,
            "rating": "7.6",
            "backdrop": "https://image.tmdb.org/t/p/w500_and_h282_face/eAPqbbHFZBrsTcZhxnoWChq2nX4.jpg"
          },
          "video": ""
        },
        {
          "episode": 6,
          "name": "Solace",
          "info": {
            "poster": "https://image.tmdb.org/t/p/w227_and_h127_bestv2/9FGGWwBZeN8YrNmcgIyG8QNnJ6T.jpg",
            "plot": "Survivors from battle return to Reach. John confronts Dr. Halsey, and the lies of his past. The new prisoner seems to know John better than he knows himself. Determined to understand more, John turns back to the mystery artifact, which shows him something truly startling.",
            "director": [],
            "duration": 2880,
            "rating": "7.4",
            "backdrop": "https://image.tmdb.org/t/p/w500_and_h282_face/9FGGWwBZeN8YrNmcgIyG8QNnJ6T.jpg"
          },
          "video": ""
        },
        {
          "episode": 7,
          "name": "Inheritance",
          "info": {
            "poster": "https://image.tmdb.org/t/p/w227_and_h127_bestv2/qvt1RzfgEUejE9dWqXjyX3xaQtk.jpg",
            "plot": "Kwan\u2019s journey to uncover her family\u2019s \u201ctrue purpose\u201d takes her deep into the deserts of Madrigal. Soren obsesses over unfinished business.",
            "director": [],
            "duration": 3060,
            "rating": "5.9",
            "backdrop": "https://image.tmdb.org/t/p/w500_and_h282_face/qvt1RzfgEUejE9dWqXjyX3xaQtk.jpg"
          },
          "video": ""
        },
        {
          "episode": 8,
          "name": "Allegiance",
          "info": {
            "poster": "https://image.tmdb.org/t/p/w227_and_h127_bestv2/ww9Q1pDeWV0LsOCD6v3uXYaX5SH.jpg",
            "plot": "John and Makee come to terms with their shared vision. Halsey has one last chance to save her mission, and herself. As things come to a head, everyone must choose a side.",
            "director": [],
            "duration": 2880,
            "rating": "7.2",
            "backdrop": "https://image.tmdb.org/t/p/w500_and_h282_face/ww9Q1pDeWV0LsOCD6v3uXYaX5SH.jpg"
          },
          "video": ""
        },
        {
          "episode": 9,
          "name": "Transcendence",
          "info": {
            "poster": "https://image.tmdb.org/t/p/w227_and_h127_bestv2/AkSS0MyRpjbQ6WrOhIwQw4t7Ea8.jpg",
            "plot": "Beaten, battered, and betrayed, John 117 leads the Spartans on a suicide mission to find the Halo and save humanity. But at what price?",
            "director": [],
            "duration": 2880,
            "rating": "7.4",
            "backdrop": "https://image.tmdb.org/t/p/w500_and_h282_face/AkSS0MyRpjbQ6WrOhIwQw4t7Ea8.jpg"
          },
          "video": ""
        }
      ]
    },
    {
      "season": 2,
      "info": {
        "poster": "https://image.tmdb.org/t/p/w220_and_h330_face/hJAHL3lsCmBnOqgNUp3aw8DXHKi.jpg",
        "bg": "https://image.tmdb.org/t/p/w500_and_h282_face",
        "plot": "In season two, Master Chief John-117 leads his team of elite Spartans against the alien threat known as the Covenant. In the wake of a shocking event on a desolate planet, John cannot shake the feeling that his war is about to change and risks everything to prove what no one else will believe \u2013 that the Covenant is preparing to attack humanity's greatest stronghold. With the galaxy on the brink, John embarks on a journey to find the key to humankind\u2019s salvation, or its extinction: the Halo.",
        "year": "2024",
        "trailer": ""
      },
      "episodes": [
        {
          "episode": 1,
          "name": "Sanctuary",
          "info": {
            "poster": "https://image.tmdb.org/t/p/w227_and_h127_bestv2/uCv8zgK3ofjqTMePUMaWenpEEYj.jpg",
            "plot": "A deadly evacuation mission signals a shift in Master Chief's war with the Covenant. On Reach, a new regime takes the reins at FLEETCOM. John senses a looming threat close to home.",
            "director": [],
            "duration": 3480,
            "rating": "7.818",
            "backdrop": "https://image.tmdb.org/t/p/w500_and_h282_face/uCv8zgK3ofjqTMePUMaWenpEEYj.jpg"
          },
          "video": ""
        },
        {
          "episode": 2,
          "name": "Sword",
          "info": {
            "poster": "https://image.tmdb.org/t/p/w227_and_h127_bestv2/AlITMrGUAiq0PQ3EMdcXanix4r0.jpg",
            "plot": "John pushes Silver Team to its limit as he searches for missing Spartans; Kai worries about John's stability. Kwan finds the Rubble is a far more dangerous place in Soren's absence. Halsey seeks the identity of her captor.",
            "director": [],
            "duration": 2820,
            "rating": "7.7",
            "backdrop": "https://image.tmdb.org/t/p/w500_and_h282_face/AlITMrGUAiq0PQ3EMdcXanix4r0.jpg"
          },
          "video": ""
        },
        {
          "episode": 3,
          "name": "Visegrad",
          "info": {
            "poster": "https://image.tmdb.org/t/p/w227_and_h127_bestv2/u5fBfZjr4EfA2vs9h9Mf20ksGc9.jpg",
            "plot": "John and Silver Team embark on an unsanctioned mission. Laera, Kwan and Kessler must escape Soren's mutinous crew. Ackerson receives troubling intelligence from Cortana. The threat of an attack forces Ackerson to make an irrevocable decision.",
            "director": [],
            "duration": 3240,
            "rating": "7.4",
            "backdrop": "https://image.tmdb.org/t/p/w500_and_h282_face/u5fBfZjr4EfA2vs9h9Mf20ksGc9.jpg"
          },
          "video": ""
        },
        {
          "episode": 4,
          "name": "Reach",
          "info": {
            "poster": "https://image.tmdb.org/t/p/w227_and_h127_bestv2/v38ILwFzXjF1ULelSyLgfTApxjF.jpg",
            "plot": "A Covenant assault threatens humanity's most important stronghold. John, Perez and Silver Team fight an overwhelming enemy. Adm. Keyes rallies the UNSC forces to make a stand. Halsey and Soren must work together to escape captivity.",
            "director": [],
            "duration": 2760,
            "rating": "8.2",
            "backdrop": "https://image.tmdb.org/t/p/w500_and_h282_face/v38ILwFzXjF1ULelSyLgfTApxjF.jpg"
          },
          "video": ""
        },
        {
          "episode": 5,
          "name": "Aleria",
          "info": {
            "poster": "https://image.tmdb.org/t/p/w227_and_h127_bestv2/82jr9i1Mj16QZ8q4ejd4BmOw8ua.jpg",
            "plot": "In the aftermath of defeat, the survivors struggle to pick up the pieces. On the desolate planet of Aleria, John grapples with an unprecedented loss. Soren and Laera search for their missing son. Makee treads carefully as the Arbiter grows impatient.",
            "director": [],
            "duration": 3720,
            "rating": "7.8",
            "backdrop": "https://image.tmdb.org/t/p/w500_and_h282_face/82jr9i1Mj16QZ8q4ejd4BmOw8ua.jpg"
          },
          "video": ""
        },
        {
          "episode": 6,
          "name": "Onyx",
          "info": {
            "poster": "https://image.tmdb.org/t/p/w227_and_h127_bestv2/EuwvYvTYhxCpIqtdMtP7V3a6zm.jpg",
            "plot": "John seeks revenge on a secret ONI planet. Perez trains to become a new kind of soldier. Kai finds herself torn between her Spartan code and her loyalty to Master Chief. Makee turns to Cortana for help in her search for the Halo.",
            "director": [],
            "duration": 3240,
            "rating": "8.3",
            "backdrop": "https://image.tmdb.org/t/p/w500_and_h282_face/EuwvYvTYhxCpIqtdMtP7V3a6zm.jpg"
          },
          "video": ""
        },
        {
          "episode": 7,
          "name": "Thermopylae",
          "info": {
            "poster": "https://image.tmdb.org/t/p/w227_and_h127_bestv2/fXv7OeYXjjPq8Y6QKX8I3YMCVkp.jpg",
            "plot": "John-117 comes face to face with Makee. A revelation leads Ackerson to question his loyalties. Soren and Laera's relationship begins to fracture. Halsey, Kwan and Miranda work to solve a mystery.",
            "director": [],
            "duration": 2880,
            "rating": "8.2",
            "backdrop": "https://image.tmdb.org/t/p/w500_and_h282_face/fXv7OeYXjjPq8Y6QKX8I3YMCVkp.jpg"
          },
          "video": ""
        },
        {
          "episode": 8,
          "name": "Halo",
          "info": {
            "poster": "https://image.tmdb.org/t/p/w227_and_h127_bestv2/gxpRvWI551hkMLT9U4QNmLJfqzw.jpg",
            "plot": "The climactic battle for the Halo begins. John makes a fateful choice. Soren and Kwan undertake a rescue mission. Halsey and Miranda unleash an ancient horror.",
            "director": [],
            "duration": 3300,
            "rating": "8.8",
            "backdrop": "https://image.tmdb.org/t/p/w500_and_h282_face/gxpRvWI551hkMLT9U4QNmLJfqzw.jpg"
          },
          "video": ""
        }
      ]
    }
  ]
}