<?xml version="1.0" encoding="UTF-8"?>
<channels>
  <channel site="cosmote.gr" lang="el" xmltv_id="AEpsilon.gr" site_id="a-epsilon">α.Epsilon</channel>
  <channel site="cosmote.gr" lang="el" xmltv_id="Action24.gr" site_id="action-24">Action 24</channel>
  <channel site="cosmote.gr" lang="el" xmltv_id="AlphaTV.gr" site_id="alpha-hd">Alpha</channel>
  <channel site="cosmote.gr" lang="el" xmltv_id="ANT1.gr" site_id="ant1-hd">ANT1</channel>
  <channel site="cosmote.gr" lang="el" xmltv_id="BerginaTV.gr" site_id="bergina-tv">Βεργίνα TV</channel>
  <channel site="cosmote.gr" lang="el" xmltv_id="CosmoteCinema1.gr" site_id="cosmote-cinema-1hd">Cosmote Cinema 1</channel>
  <channel site="cosmote.gr" lang="el" xmltv_id="CosmoteCinema2.gr" site_id="cosmote-cinema-2-hd">Cosmote Cinema 2</channel>
  <channel site="cosmote.gr" lang="el" xmltv_id="CosmoteCinema3.gr" site_id="cosmote-cinema-3">Cosmote Cinema 3</channel>
  <channel site="cosmote.gr" lang="el" xmltv_id="CosmoteCinemaKids.gr" site_id="cosmote-cinema-kids-hd">Cosmote Cinema Kids</channel>
  <channel site="cosmote.gr" lang="el" xmltv_id="CosmoteHistory.gr" site_id="cosmote-history-hd">Cosmote History</channel>
  <channel site="cosmote.gr" lang="el" xmltv_id="CosmoteSeries.gr" site_id="cosmote-series-hd">Cosmote Series</channel>
  <channel site="cosmote.gr" lang="el" xmltv_id="CosmoteSport1.gr" site_id="cosmote-sport-1hd">Cosmote Sport 1</channel>
  <channel site="cosmote.gr" lang="el" xmltv_id="CosmoteSport2.gr" site_id="cosmote-sport-2hd">Cosmote Sport 2</channel>
  <channel site="cosmote.gr" lang="el" xmltv_id="CosmoteSport3.gr" site_id="cosmote-sport-3hd">Cosmote Sport 3</channel>
  <channel site="cosmote.gr" lang="el" xmltv_id="CosmoteSport4.gr" site_id="cosmote-sport-4hd">Cosmote Sport 4</channel>
  <channel site="cosmote.gr" lang="el" xmltv_id="CosmoteSport4K.gr" site_id="cosmote-sport-4k">Cosmote Sport 4K</channel>
  <channel site="cosmote.gr" lang="el" xmltv_id="CosmoteSport5.gr" site_id="cosmote-sport-5hd">Cosmote Sport 5</channel>
  <channel site="cosmote.gr" lang="el" xmltv_id="CosmoteSport6.gr" site_id="cosmote-sport-6hd">Cosmote Sport 6</channel>
  <channel site="cosmote.gr" lang="el" xmltv_id="CosmoteSport7.gr" site_id="cosmote-sport-7hd">Cosmote Sport 7</channel>
  <channel site="cosmote.gr" lang="el" xmltv_id="CosmoteSport8.gr" site_id="cosmote-sport-8hd">Cosmote Sport 8</channel>
  <channel site="cosmote.gr" lang="el" xmltv_id="CosmoteSport9.gr" site_id="cosmote-sport-9hd">Cosmote Sport 9</channel>
  <channel site="cosmote.gr" lang="el" xmltv_id="CosmoteSportHighlights.gr" site_id="cosmote-sport-highlights-hd">Cosmote Sport Highlights</channel>
  <channel site="cosmote.gr" lang="el" xmltv_id="DisneyJunior" site_id="disney-junior">Disney Junior</channel>
  <channel site="cosmote.gr" lang="el" xmltv_id="ENAChannel.gr" site_id="ena-channel">ENA Channel</channel>
  <channel site="cosmote.gr" lang="el" xmltv_id="EPTNews.gr" site_id="ert-news">ΕΡΤ News</channel>
  <channel site="cosmote.gr" lang="el" xmltv_id="ΕΡΤ1.gr" site_id="ert1-hd">ΕΡΤ1</channel>
  <channel site="cosmote.gr" lang="el" xmltv_id="ΕΡΤ2.gr" site_id="ert2-hd">ΕΡΤ2</channel>
  <channel site="cosmote.gr" lang="el" xmltv_id="ΕΡΤ3.gr" site_id="ert3-hd">ΕΡΤ3</channel>
  <channel site="cosmote.gr" lang="el" xmltv_id="Euronews.gr" site_id="euronews-greek">euronews</channel>
  <channel site="cosmote.gr" lang="el" xmltv_id="FTV.gr" site_id="ftv-hd">FTV</channel>
  <channel site="cosmote.gr" lang="el" xmltv_id="FX.gr" site_id="fx">FX</channel>
  <channel site="cosmote.gr" lang="el" xmltv_id="FXLife.gr" site_id="fx-life">FX Life</channel>
  <channel site="cosmote.gr" lang="el" xmltv_id="Kontra.gr" site_id="kontra-channel">Kontra</channel>
  <channel site="cosmote.gr" lang="el" xmltv_id="NEA.gr" site_id="krete-nea-teleorase">Κρήτη Νέα Τηλεόραση</channel>
  <channel site="cosmote.gr" lang="el" xmltv_id="MADViral.gr" site_id="mad-viral-hd">MAD Viral</channel>
  <channel site="cosmote.gr" lang="el" xmltv_id="MakedoniaTV.gr" site_id="makedonia-tv-hd">Μακεδονία TV</channel>
  <channel site="cosmote.gr" lang="el" xmltv_id="Naftemporiki.gr" site_id="naftemporiki">Naftemporiki</channel>
  <channel site="cosmote.gr" lang="el" xmltv_id="NationalGeographic.gr" site_id="national-geographic-hd">National Geographic</channel>
  <channel site="cosmote.gr" lang="el" xmltv_id="Nickelodeon.gr" site_id="nickelodeon-hd">Nickelodeon</channel>
  <channel site="cosmote.gr" lang="el" xmltv_id="OneChannel.gr" site_id="one-channel-hd">ONE Channel</channel>
  <channel site="cosmote.gr" lang="el" xmltv_id="OpenBeyond.gr" site_id="open-beyond-hd">Open Beyond</channel>
  <channel site="cosmote.gr" lang="el" xmltv_id="PanikTV.gr" site_id="panik-tv">Panik TV</channel>
  <channel site="cosmote.gr" lang="el" xmltv_id="Skai.gr" site_id="skai-hd">ΣΚΑΪ</channel>
  <channel site="cosmote.gr" lang="el" xmltv_id="Star.gr" site_id="star-hd">Star</channel>
  <channel site="cosmote.gr" lang="el" xmltv_id="TCM.gr" site_id="tcm-hd">TCM HD</channel>
  <channel site="cosmote.gr" lang="el" xmltv_id="ViasatExplore.gr" site_id="viasat-explore-hd">Viasat Explore</channel>
  <channel site="cosmote.gr" lang="el" xmltv_id="ViasatHistory.gr" site_id="viasat-history-hd">Viasat History</channel>
  <channel site="cosmote.gr" lang="el" xmltv_id="ViasatNature.gr" site_id="viasat-nature-hd">Viasat Nature</channel>
  <channel site="cosmote.gr" lang="el" xmltv_id="4E.gr" site_id="4e">4Ε</channel>
  <channel site="cosmote.gr" lang="el" xmltv_id="AigaioTV.gr" site_id="aigaio-tv">Αιγαίο TV</channel>
  <channel site="cosmote.gr" lang="el" xmltv_id="BabyTV.gr" site_id="baby-tv">Baby TV</channel>
  <channel site="cosmote.gr" lang="el" xmltv_id="BBCEarth.gr" site_id="bbc-earth-hd">BBC Earth</channel>
  <channel site="cosmote.gr" lang="el" xmltv_id="BloombergTVEurope.uk" site_id="bloomberg">Bloomberg TV</channel>
  <channel site="cosmote.gr" lang="el" xmltv_id="CBSReality.gr" site_id="cbs-reality">CBS Reality</channel>
  <channel site="cosmote.gr" lang="el" xmltv_id="CNBCEurope.uk" site_id="cnbc">CNBC</channel>
  <channel site="cosmote.gr" lang="el" xmltv_id="CNNInternational.us" site_id="cnn">CNN</channel>
  <channel site="cosmote.gr" lang="el" xmltv_id="CrimePlusInvestigation.gr" site_id="crime-and-investigation">Crime and Investigation</channel>
  <channel site="cosmote.gr" lang="el" xmltv_id="DisneyChannel.gr" site_id="disney-channel">Disney Channel</channel>
  <channel site="cosmote.gr" lang="el" xmltv_id="EDGEsport.gr" site_id="edgesport-hd">EDGEsport</channel>
  <channel site="cosmote.gr" lang="el" xmltv_id="EEntertainment.gr" site_id="e-hd">E!</channel>
  <channel site="cosmote.gr" lang="el" xmltv_id="TV100.gr" site_id="tv100">TV100</channel>
  <channel site="cosmote.gr" lang="el" xmltv_id="ERTWorld.gr" site_id="ert-world">ERT World</channel>
  <channel site="novasports.gr" lang="el" xmltv_id="Eurosport1.gr" site_id="Eurosport 1 HD">Eurosport 1</channel>
  <channel site="novasports.gr" lang="el" xmltv_id="Eurosport2.gr" site_id="Eurosport 2 HD">Eurosport 2</channel>
  <channel site="cosmote.gr" lang="el" xmltv_id="VouliTV.gr" site_id="boule">ΒΟΥΛΗ</channel>
  <channel site="cosmote.gr" lang="el" xmltv_id="KritiTV.gr" site_id="krete-tv">ΚΡΗΤΗ TV</channel>
  <channel site="cosmote.gr" lang="el" xmltv_id="LuxeTV.lu" site_id="luxe-tv-hd">Luxe TV HD</channel>
  <channel site="cosmote.gr" lang="el" xmltv_id="MadTV.gr" site_id="mad">MAD</channel>
  <channel site="cosmote.gr" lang="el" xmltv_id="Mega.gr" site_id="mega-hd">MEGA HD</channel>
  <channel site="cosmote.gr" lang="el" xmltv_id="MTVGlobal.uk" site_id="mtv-europe">MTV Europe</channel>
  <channel site="cosmote.gr" lang="el" xmltv_id="NationalGeographicWild.gr" site_id="nat-geo-wild-hd">National Geographic Wild</channel>
  <channel site="novasports.gr" lang="el" xmltv_id="Novasports1.gr" site_id="Novasports1HD">Novasports 1</channel>
  <channel site="novasports.gr" lang="el" xmltv_id="Novasports2.gr" site_id="Novasports2HD">Novasports 2</channel>
  <channel site="novasports.gr" lang="el" xmltv_id="Novasports3.gr" site_id="Novasports3HD">Novasports 3</channel>
  <channel site="novasports.gr" lang="el" xmltv_id="Novasports4.gr" site_id="Novasports4HD">Novasports 4</channel>
  <channel site="novasports.gr" lang="el" xmltv_id="Novasports5.gr" site_id="Novasports5HD">Novasports 5</channel>
  <channel site="novasports.gr" lang="el" xmltv_id="Novasports6.gr" site_id="Novasports6HD">Novasports 6</channel>
  <channel site="novasports.gr" lang="el" xmltv_id="NovasportsExtra1.gr" site_id="Novasports Εxtra1">Novasports Εxtra 1</channel>
  <channel site="novasports.gr" lang="el" xmltv_id="NovasportsExtra2.gr" site_id="Novasports Extra2">Novasports Extra 2</channel>
  <channel site="novasports.gr" lang="el" xmltv_id="NovasportsExtra3.gr" site_id="Novasports Extra3">Novasports Extra 3</channel>
  <channel site="novasports.gr" lang="el" xmltv_id="NovasportsExtra4.gr" site_id="Novasports Extra4">Novasports Extra 4</channel>
  <channel site="novasports.gr" lang="el" xmltv_id="NovasportsNews.gr" site_id="ΝovasportsNews">Νovasports News</channel>
  <channel site="novasports.gr" lang="el" xmltv_id="NovasportsPremierLeague.gr" site_id="Novasports Premier League">Novasports Premier League</channel>
  <channel site="novasports.gr" lang="el" xmltv_id="NovasportsPrime.gr" site_id="Novasports Prime">Novasports Prime</channel>
  <channel site="novasports.gr" lang="el" xmltv_id="NovasportsStart.gr" site_id="ΝovasportsStart">Νovasports Start</channel>
  <channel site="cosmote.gr" lang="el" xmltv_id="SmileTV.gr" site_id="smile-tv">Smile TV</channel>
  <channel site="cosmote.gr" lang="el" xmltv_id="StarKentrikisElladas.gr" site_id="star-kentrikes-elladas">Star Κεντρικής Ελλάδας</channel>
  <channel site="cosmote.gr" lang="el" xmltv_id="VillageCinemas.gr" site_id="village-cinema-hd">Village Cinema HD</channel>
</channels>
